firmitas/__init__.py
firmitas/base/__init__.py
firmitas/base/maintool.py
firmitas/conf/__init__.py
firmitas/conf/certlist.yml
firmitas/conf/certlist.yml.save
firmitas/conf/logrdata.py
firmitas/conf/standard.py
firmitas/main.py
firmitas/unit/__init__.py
firmitas/unit/gogithub.py
firmitas/unit/gogitlab.py
firmitas/unit/gopagure.py
firmitas-0.1.4.dist-info/LICENSE
firmitas-0.1.4.dist-info/METADATA
firmitas-0.1.4.dist-info/WHEEL
firmitas-0.1.4.dist-info/entry_points.txt
firmitas-0.1.4.dist-info/RECORD
