Metadata-Version: 2.1
Name: firmitas
Version: 0.1.4
Summary: Simple notification service for X.509-standard TLS certificate statuses
Home-page: https://gitlab.com/t0xic0der/firmitas/
License: GPL-3.0-or-later
Keywords: notification,security,certificate
Author: Akashdeep Dhar
Author-email: akashdeep.dhar@gmail.com
Maintainer: Akashdeep Dhar
Maintainer-email: akashdeep.dhar@gmail.com
Requires-Python: >=3.8,<4
Classifier: Development Status :: 4 - Beta
Classifier: Intended Audience :: Developers
Classifier: Intended Audience :: System Administrators
Classifier: License :: OSI Approved :: GNU General Public License v3 or later (GPLv3+)
Classifier: Natural Language :: English
Classifier: Operating System :: POSIX :: Linux
Classifier: Programming Language :: Python :: 3
Classifier: Programming Language :: Python :: 3.8
Classifier: Programming Language :: Python :: 3.9
Classifier: Programming Language :: Python :: 3.10
Classifier: Programming Language :: Python :: 3.11
Classifier: Programming Language :: Python :: 3.12
Classifier: Topic :: Security
Classifier: Topic :: Security :: Cryptography
Classifier: Topic :: System :: Networking
Classifier: Topic :: System :: Networking :: Monitoring
Classifier: Topic :: System :: Operating System
Requires-Dist: click (>=8.0.0,<9)
Requires-Dist: cryptography (>=36.0.0)
Requires-Dist: pyyaml (>=5.0.0,<7)
Requires-Dist: requests (>=2.20.0,<3)
Project-URL: Documentation, https://gitlab.com/t0xic0der/firmitas/-/blob/main/README.md
Project-URL: Repository, https://gitlab.com/t0xic0der/firmitas/
